odoo/addons/product_packaging_level_vendor/README.rst
odoo/addons/product_packaging_level_vendor/__init__.py
odoo/addons/product_packaging_level_vendor/__manifest__.py
odoo/addons/product_packaging_level_vendor/i18n/it.po
odoo/addons/product_packaging_level_vendor/i18n/product_packaging_level_vendor.pot
odoo/addons/product_packaging_level_vendor/i18n/product_packaging_type_vendor.pot
odoo/addons/product_packaging_level_vendor/models/__init__.py
odoo/addons/product_packaging_level_vendor/models/product_packaging_level.py
odoo/addons/product_packaging_level_vendor/readme/CONTRIBUTORS.md
odoo/addons/product_packaging_level_vendor/readme/CREDITS.md
odoo/addons/product_packaging_level_vendor/readme/DESCRIPTION.md
odoo/addons/product_packaging_level_vendor/static/description/icon.png
odoo/addons/product_packaging_level_vendor/static/description/index.html
odoo/addons/product_packaging_level_vendor/views/product_packaging_level_view.xml
odoo_addon_product_packaging_level_vendor-18.0.1.0.0.3.dist-info/METADATA
odoo_addon_product_packaging_level_vendor-18.0.1.0.0.3.dist-info/WHEEL
odoo_addon_product_packaging_level_vendor-18.0.1.0.0.3.dist-info/top_level.txt
odoo_addon_product_packaging_level_vendor-18.0.1.0.0.3.dist-info/RECORD
